mwthesaurus/__init__.py
mwthesaurus/client.py
mwthesaurus/model.py
mwthesaurus-0.1.2.dist-info/LICENSE
mwthesaurus-0.1.2.dist-info/WHEEL
mwthesaurus-0.1.2.dist-info/METADATA
mwthesaurus-0.1.2.dist-info/RECORD
