Metadata-Version: 2.1
Name: mwthesaurus
Version: 0.1.2
Summary: API Wrapper for the Merriam-Webster Collegiate Thesaurus API.
Home-page: https://github.com/PederHA/mwthesaurus
License: MIT
Author: Peder Hovdan Andresen
Requires-Python: >=3.7,<4.0
Classifier: License :: OSI Approved :: MIT License
Classifier: Programming Language :: Python :: 3
Classifier: Programming Language :: Python :: 3.7
Classifier: Programming Language :: Python :: 3.8
Requires-Dist: httpx (>=0.13.0,<0.14.0)
Project-URL: Repository, https://github.com/PederHA/mwthesaurus
